MANIFEST.in
README.md
setup.py
src/agile_item_master/AgileAPI.jar
src/agile_item_master/__init__.py
src/agile_item_master/__version__.py
src/agile_item_master/agile.py
src/agile_item_master/attachments.py
src/agile_item_master/changes.py
src/agile_item_master/explode.py
src/agile_item_master/items.py
src/agile_item_master/session.py
src/agile_item_master/sku_generator.py
src/agile_item_master/tables.py
src/agile_item_master/utils.py
src/agile_item_master/workato.py
src/agile_item_master/workbook.py
src/agile_item_master.egg-info/PKG-INFO
src/agile_item_master.egg-info/SOURCES.txt
src/agile_item_master.egg-info/dependency_links.txt
src/agile_item_master.egg-info/entry_points.txt
src/agile_item_master.egg-info/namespace_packages.txt
src/agile_item_master.egg-info/not-zip-safe
src/agile_item_master.egg-info/requires.txt
src/agile_item_master.egg-info/top_level.txt